macrocosm_visual/__init__.py
macrocosm_visual/visual_configs.yaml
macrocosm_visual/viz_setup.py
macrocosm_visual-0.1.4.dist-info/licenses/LICENSE.md
macrocosm_visual-0.1.4.dist-info/METADATA
macrocosm_visual-0.1.4.dist-info/WHEEL
macrocosm_visual-0.1.4.dist-info/top_level.txt
macrocosm_visual-0.1.4.dist-info/RECORD
