Metadata-Version: 2.4
Name: macrocosm-visual
Version: 0.1.4
Summary: Macrocosm Visual Engine
Home-page: https://github.com/macro-cosm/macrocosm-visual
Author: Macrocosm
Author-email: luca.mungo@macrocosm.group
License: MIT
License-File: LICENSE.md
Requires-Dist: pyyaml
Requires-Dist: matplotlib
Requires-Dist: plotly
Dynamic: author
Dynamic: author-email
Dynamic: description
Dynamic: description-content-type
Dynamic: home-page
Dynamic: license
Dynamic: license-file
Dynamic: requires-dist
Dynamic: summary
